LICENSE.txt
README.md
setup.py
pretty_midi/TimGM6mb.sf2
pretty_midi/__init__.py
pretty_midi/constants.py
pretty_midi/containers.py
pretty_midi/fluidsynth.py
pretty_midi/instrument.py
pretty_midi/pretty_midi.py
pretty_midi/utilities.py
pretty_midi.egg-info/PKG-INFO
pretty_midi.egg-info/SOURCES.txt
pretty_midi.egg-info/dependency_links.txt
pretty_midi.egg-info/requires.txt
pretty_midi.egg-info/top_level.txt
tests/test_pretty_midi.py
tests/test_utilities.py