Metadata-Version: 2.1
Name: pretty_midi
Version: 0.2.11
Summary: Functions and classes for handling MIDI data conveniently.
Home-page: https://github.com/craffel/pretty-midi
Author: Colin Raffel
Author-email: craffel@gmail.com
License: MIT
Keywords: audio music midi mir
Classifier: License :: OSI Approved :: MIT License
Classifier: Programming Language :: Python
Classifier: Development Status :: 3 - Alpha
Classifier: Intended Audience :: Developers
Classifier: Topic :: Multimedia :: Sound/Audio :: MIDI
License-File: LICENSE.txt
Requires-Dist: numpy>=1.7.0
Requires-Dist: mido>=1.1.16
Requires-Dist: six
Requires-Dist: importlib_resources
Provides-Extra: fluidsynth
Requires-Dist: pyfluidsynth>=1.3.1; extra == "fluidsynth"
